[
  { "id": 1, "user_id": 101, "store_name": "North Grain Studio", "slug": "north-grain-studio", "approval_status": "approved", "short_bio": "Solid oak dining and living pieces made in small batches.", "country": "Denmark", "city": "Aarhus", "lead_time_min_days": 14, "lead_time_max_days": 35, "rating_average": 4.9, "review_count": 28, "response_time_hours": 6, "accepts_custom_orders": true, "featured_image_url": "https://images.unsplash.com/photo-1513694203232-719a280e022f" },
  { "id": 2, "user_id": 102, "store_name": "Atelier Rowan", "slug": "atelier-rowan", "approval_status": "approved", "short_bio": "Warm walnut furniture with sculptural joinery.", "country": "France", "city": "Lyon", "lead_time_min_days": 21, "lead_time_max_days": 45, "rating_average": 4.8, "review_count": 19, "response_time_hours": 8, "accepts_custom_orders": true, "featured_image_url": "https://images.unsplash.com/photo-1505693416388-ac5ce068fe85" },
  { "id": 3, "user_id": 103, "store_name": "Forge & Timber", "slug": "forge-and-timber", "approval_status": "approved", "short_bio": "Wood and steel furniture for bold interiors.", "country": "United Kingdom", "city": "Bristol", "lead_time_min_days": 10, "lead_time_max_days": 28, "rating_average": 4.7, "review_count": 14, "response_time_hours": 5, "accepts_custom_orders": false, "featured_image_url": "https://images.unsplash.com/photo-1493663284031-b7e3aefcae8e" },
  { "id": 4, "user_id": 104, "store_name": "Studio Verdant", "slug": "studio-verdant", "approval_status": "pending", "short_bio": "Soft modern bedroom pieces built from ash and linen accents.", "country": "Netherlands", "city": "Utrecht", "lead_time_min_days": 18, "lead_time_max_days": 40, "rating_average": 4.6, "review_count": 9, "response_time_hours": 10, "accepts_custom_orders": true, "featured_image_url": "https://images.unsplash.com/photo-1505693416388-ac5ce068fe85" },
  { "id": 5, "user_id": 105, "store_name": "Mora Workshop", "slug": "mora-workshop", "approval_status": "approved", "short_bio": "Mediterranean-inspired consoles, benches, and detail pieces.", "country": "Spain", "city": "Valencia", "lead_time_min_days": 12, "lead_time_max_days": 30, "rating_average": 4.9, "review_count": 11, "response_time_hours": 7, "accepts_custom_orders": true, "featured_image_url": "https://images.unsplash.com/photo-1549187774-b4e9b0445b41" }
]
